{"id":"bitcoin","symbol":"btc","name":"Bitcoin","localization":{"en":"Bitcoin","de":"Bitcoin","es":"Bitcoin","fr":"Bitcoin","it":"Bitcoin","pl":"Bitcoin","ro":"Bitcoin","hu":"Bitcoin","nl":"Bitcoin","pt":"Bitcoin","sv":"Bitcoin","vi":"Bitcoin","tr":"Bitcoin","ru":"биткоин","ja":"ビットコイン","zh":"比特币","zh-tw":"比特幣","ko":"비트코인","ar":"بيتكوين","th":"บิตคอยน์","id":"Bitcoin"},"image":{"thumb":"https://assets.coingecko.com/coins/images/1/thumb/bitcoin.png?1547033579","small":"https://assets.coingecko.com/coins/images/1/small/bitcoin.png?1547033579"},"market_data":{"current_price":{"aud":null,"bdt":34531.64937425,"bhd":167.842785775,"bmd":445.165,"brl":null,"btc":1.0,"cad":483.6704,"chf":397.0707,"cny":2788.6725,"dkk":null,"eur":325.0239,"gbp":264.7699,"hkd":3451.0472,"idr":null,"inr":null,"jpy":45220.5747,"krw":456121.9713,"ltc":42.82655246252677,"mmk":428424.25855950004,"mxn":null,"myr":null,"ngn":72291.10157566502,"nzd":null,"php":null,"pln":null,"rub":15475.93,"sek":2921.8413,"sgd":557.0007,"twd":13418.5929,"uah":5280.102065000001,"usd":445.165,"vef":2802.258029375,"vnd":9401818.025249999,"xag":null,"xau":null,"xdr":288.0357,"zar":null},"market_cap":{"aud":null,"brl":null,"btc":null,"cad":null,"chf":null,"cny":null,"dkk":null,"eur":null,"gbp":null,"hkd":null,"idr":null,"inr":null,"jpy":null,"krw":null,"mxn":null,"myr":null,"ngn":929727875812.5234,"nzd":null,"php":null,"pln":null,"rub":null,"sek":null,"sgd":null,"twd":null,"uah":67906809689.815,"usd":5725217915.0,"vnd":120915743582112.73,"xag":null,"xau":null,"xdr":null,"zar":null},"total_volume":{"aud":5651246.915325337,"bdt":410578897.1216232,"bhd":1995638.989798966,"bmd":5292980.730698652,"brl":11707432.746871904,"btc":11889.9300949056,"cad":5750807.2449750295,"chf":4721142.865735233,"cny":33157121.082585637,"dkk":28838375.06601734,"eur":3864511.4501735885,"gbp":3148095.6022351463,"hkd":41032709.96221971,"idr":60383795832.88383,"inr":310942412.775839,"jpy":537669472.0344567,"krw":5423258353.507539,"ltc":509204.71498525055,"mmk":5093934485.234218,"mxn":68290045.35372716,"myr":17091068.24957916,"ngn":859536144.218377,"nzd":6132147.02794389,"php":231565816.1238588,"pln":16189995.84230179,"rub":184007725.85365242,"sek":34740488.805408105,"sgd":6622699.385813487,"twd":159546131.5529966,"uah":62780044.44681671,"usd":5292980.730698652,"vef":33318652.077156674,"vnd":111786959085.24591,"xag":273705.0017917174,"xau":4092.5139386665073,"xdr":3424724.337837201,"zar":54782627.003605746}},"community_data":{"facebook_likes":null,"twitter_followers":51685,"reddit_average_posts_48h":5.34,"reddit_average_comments_48h":404.915,"reddit_subscribers":120525,"reddit_accounts_active_48h":"712.0"},"developer_data":{"forks":3769,"stars":5394,"subscribers":763,"total_issues":4187,"closed_issues":3805,"pull_requests_merged":1880,"pull_request_contributors":193,"code_additions_deletions_4_weeks":{"additions":null,"deletions":null},"commit_count_4_weeks":null},"public_interest_stats":{"alexa_rank":null,"bing_matches":null}}