{"id":"bitcoin","symbol":"btc","name":"Bitcoin","localization":{"en":"Bitcoin","de":"Bitcoin","es":"Bitcoin","fr":"Bitcoin","it":"Bitcoin","pl":"Bitcoin","ro":"Bitcoin","hu":"Bitcoin","nl":"Bitcoin","pt":"Bitcoin","sv":"Bitcoin","vi":"Bitcoin","tr":"Bitcoin","ru":"биткоин","ja":"ビットコイン","zh":"比特币","zh-tw":"比特幣","ko":"비트코인","ar":"بيتكوين","th":"บิตคอยน์","id":"Bitcoin"},"image":{"thumb":"https://assets.coingecko.com/coins/images/1/thumb/bitcoin.png?1547033579","small":"https://assets.coingecko.com/coins/images/1/small/bitcoin.png?1547033579"},"market_data":{"current_price":{"aud":null,"bdt":32692.698235800002,"bhd":158.60270178000002,"bmd":420.66,"brl":null,"btc":1.0,"cad":461.6108,"chf":368.4923,"cny":2609.2543,"dkk":null,"eur":302.9619,"gbp":251.402,"hkd":3261.3803,"idr":null,"inr":null,"jpy":42745.028,"krw":435753.9504,"ltc":39.123630672926446,"mmk":404195.746194,"mxn":null,"myr":null,"ngn":67659.62703534,"nzd":null,"php":null,"pln":null,"rub":14999.2544,"sek":2747.1803,"sgd":525.2201,"twd":12654.7108,"uah":5298.5660544,"usd":420.66,"vef":2646.6257179800004,"vnd":8873058.50085978,"xag":null,"xau":null,"xdr":270.9719,"zar":null},"market_cap":{"aud":null,"brl":null,"btc":null,"cad":null,"chf":null,"cny":null,"dkk":null,"eur":null,"gbp":null,"hkd":null,"idr":null,"inr":null,"jpy":null,"krw":null,"mxn":null,"myr":null,"ngn":855978805222.3751,"nzd":null,"php":null,"pln":null,"rub":null,"sek":null,"sgd":null,"twd":null,"uah":67033479777.655045,"usd":5321874506.0,"vnd":112255274630276.81,"xag":null,"xau":null,"xdr":null,"zar":null},"total_volume":{"aud":20069804.547271676,"brl":41772939.20390175,"btc":44825.5261573489,"cad":null,"chf":16517861.232431658,"cny":null,"dkk":101388239.80457988,"eur":null,"gbp":null,"hkd":null,"idr":215240643098.3253,"inr":1137038249.5438335,"jpy":null,"krw":null,"ltc":1753737.330099722,"mxn":246043108.44333455,"myr":61055419.244640514,"ngn":3092421003.1735,"nzd":21710813.269260827,"php":836695054.1592442,"pln":56781354.633616075,"rub":null,"sek":null,"sgd":null,"twd":567254069.9790856,"uah":242173917.76000002,"usd":19226500.0,"vnd":405548089351.9245,"xag":944464.8710301098,"xau":14294.860291578565,"xdr":12146457.991356531,"zar":197683094.0310313}},"community_data":{"facebook_likes":null,"twitter_followers":47924,"reddit_average_posts_48h":0.0,"reddit_average_comments_48h":0.0,"reddit_subscribers":null,"reddit_accounts_active_48h":null},"developer_data":{"forks":3578,"stars":5262,"subscribers":735,"total_issues":4043,"closed_issues":3656,"pull_requests_merged":null,"pull_request_contributors":null,"code_additions_deletions_4_weeks":{"additions":null,"deletions":null},"commit_count_4_weeks":null},"public_interest_stats":{"alexa_rank":null,"bing_matches":null}}