{"id":"bitcoin","symbol":"btc","name":"Bitcoin","localization":{"en":"Bitcoin","de":"Bitcoin","es":"Bitcoin","fr":"Bitcoin","it":"Bitcoin","pl":"Bitcoin","ro":"Bitcoin","hu":"Bitcoin","nl":"Bitcoin","pt":"Bitcoin","sv":"Bitcoin","vi":"Bitcoin","tr":"Bitcoin","ru":"биткоин","ja":"ビットコイン","zh":"比特币","zh-tw":"比特幣","ko":"비트코인","ar":"بيتكوين","th":"บิตคอยน์","id":"Bitcoin"},"image":{"thumb":"https://assets.coingecko.com/coins/images/1/thumb/bitcoin.png?1547033579","small":"https://assets.coingecko.com/coins/images/1/small/bitcoin.png?1547033579"},"market_data":{"current_price":{"aud":null,"bdt":34104.089479300004,"bhd":165.6279611,"bmd":439.3,"brl":null,"btc":1.0,"cad":479.0457,"chf":382.7861,"cny":2761.0025,"dkk":null,"eur":315.7926,"gbp":259.1132,"hkd":3405.6628,"idr":null,"inr":null,"jpy":44750.832,"krw":450551.2173,"ltc":41.339396444811904,"mmk":422428.90315,"mxn":null,"myr":null,"ngn":70871.8297,"nzd":null,"php":null,"pln":null,"rub":15406.2643,"sek":2857.7796,"sgd":549.0025,"twd":13168.3332,"uah":5174.760708,"usd":439.3,"vef":2764.8061559,"vnd":9264566.0981869,"xag":null,"xau":null,"xdr":280.8201,"zar":null},"market_cap":{"aud":null,"brl":null,"btc":null,"cad":null,"chf":null,"cny":null,"dkk":null,"eur":null,"gbp":null,"hkd":null,"idr":null,"inr":null,"jpy":null,"krw":null,"mxn":null,"myr":null,"ngn":901958003965.879,"nzd":null,"php":null,"pln":null,"rub":null,"sek":null,"sgd":null,"twd":null,"uah":65857151691.24156,"usd":5590798951.0,"vnd":117906502215373.3,"xag":null,"xau":null,"xdr":null,"zar":null},"total_volume":{"aud":17447102.471278477,"bdt":1270127824.1046448,"bhd":6168429.799907669,"bmd":16360711.036365218,"brl":36193207.411306776,"btc":37242.6838979404,"cad":17840947.57776759,"chf":14255981.722825404,"cny":102827143.34892319,"dkk":87323081.07904162,"eur":11760963.979108734,"gbp":9650071.001383811,"hkd":126836023.12337461,"idr":188049914562.20096,"inr":977481295.0325508,"jpy":1666641090.345836,"krw":16779736565.736156,"ltc":1539590.0743257708,"mmk":15732386109.369131,"mxn":211220995.3512922,"myr":52914397.833656944,"ngn":2639457150.785764,"nzd":18792665.743437506,"php":719996610.9556545,"pln":49035136.56628484,"rub":573770631.373024,"sek":106431382.29278256,"sgd":20446326.566679027,"twd":490424070.830354,"uah":192721977.29552627,"usd":16360711.036365218,"vef":102968801.70326342,"vnd":345037306646.3498,"xag":842813.1094155606,"xau":12655.063988520147,"xdr":10458494.216488013,"zar":170415166.08690542}},"community_data":{"facebook_likes":null,"twitter_followers":50788,"reddit_average_posts_48h":2.364,"reddit_average_comments_48h":232.205,"reddit_subscribers":null,"reddit_accounts_active_48h":null},"developer_data":{"forks":3716,"stars":5365,"subscribers":752,"total_issues":4140,"closed_issues":3753,"pull_requests_merged":1864,"pull_request_contributors":189,"code_additions_deletions_4_weeks":{"additions":null,"deletions":null},"commit_count_4_weeks":null},"public_interest_stats":{"alexa_rank":null,"bing_matches":null}}