{"id":"bitcoin","symbol":"btc","name":"Bitcoin","localization":{"en":"Bitcoin","de":"Bitcoin","es":"Bitcoin","fr":"Bitcoin","it":"Bitcoin","pl":"Bitcoin","ro":"Bitcoin","hu":"Bitcoin","nl":"Bitcoin","pt":"Bitcoin","sv":"Bitcoin","vi":"Bitcoin","tr":"Bitcoin","ru":"биткоин","ja":"ビットコイン","zh":"比特币","zh-tw":"比特幣","ko":"비트코인","ar":"بيتكوين","th":"บิตคอยน์","id":"Bitcoin"},"image":{"thumb":"https://assets.coingecko.com/coins/images/1/thumb/bitcoin.png?1547033579","small":"https://assets.coingecko.com/coins/images/1/small/bitcoin.png?1547033579"},"market_data":{"current_price":{"aud":134.7469,"brl":275.1948,"btc":1.0,"cad":133.8223,"chf":123.5639,"cny":794.5214,"dkk":741.2621,"eur":99.3948,"gbp":85.042,"hkd":1003.7698,"idr":1267074.5924,"inr":7303.6418,"jpy":13017.0559,"krw":146104.5806,"mxn":1652.6784,"myr":399.4012,"ngn":20425.50574467,"nzd":162.0772,"php":5471.2474,"pln":424.7059,"rub":4115.3729,"sek":854.5162,"sgd":163.2781,"twd":3876.5232,"uah":1051.70436267,"usd":129.09,"xag":5.6845,"xau":0.0926,"xdr":86.256,"zar":1296.7765},"market_cap":{"aud":1513019041.34,"brl":3090052331.28,"btc":11228600.0,"cad":1502637077.78,"chf":1387449607.54,"cny":8921362992.04,"dkk":8323335616.06,"eur":1116064451.28,"gbp":954902601.2,"hkd":11270929576.28,"idr":14227473768222.64,"inr":82009672315.48,"jpy":146163313878.74,"krw":1640549893725.16,"mxn":18557264682.24,"myr":4484716314.32,"ngn":229349833804.60156,"nzd":1819900047.92,"php":61434448555.64,"pln":4768852668.74,"rub":46209876144.94,"sek":9595020603.32,"sgd":1833384473.66,"twd":43527928403.52,"uah":11809167606.676361,"usd":1449499974.0,"xag":63828976.7,"xau":1039768.36,"xdr":968534121.6,"zar":14560984607.9},"total_volume":{"aud":0.0,"brl":0.0,"btc":0.0,"cad":0.0,"chf":0.0,"cny":0.0,"dkk":0.0,"eur":0.0,"gbp":0.0,"hkd":0.0,"idr":0.0,"inr":0.0,"jpy":0.0,"krw":0.0,"mxn":0.0,"myr":0.0,"ngn":0.0,"nzd":0.0,"php":0.0,"pln":0.0,"rub":0.0,"sek":0.0,"sgd":0.0,"twd":0.0,"uah":0.0,"usd":0.0,"xag":0.0,"xau":0.0,"xdr":0.0,"zar":0.0}},"community_data":{"facebook_likes":null,"twitter_followers":null,"reddit_average_posts_48h":0.0,"reddit_average_comments_48h":0.0,"reddit_subscribers":null,"reddit_accounts_active_48h":null},"developer_data":{"forks":null,"stars":null,"subscribers":null,"total_issues":null,"closed_issues":null,"pull_requests_merged":null,"pull_request_contributors":null,"code_additions_deletions_4_weeks":{"additions":null,"deletions":null},"commit_count_4_weeks":null},"public_interest_stats":{"alexa_rank":null,"bing_matches":null}}