{"id":"bitcoin","symbol":"btc","name":"Bitcoin","localization":{"en":"Bitcoin","de":"Bitcoin","es":"Bitcoin","fr":"Bitcoin","it":"Bitcoin","pl":"Bitcoin","ro":"Bitcoin","hu":"Bitcoin","nl":"Bitcoin","pt":"Bitcoin","sv":"Bitcoin","vi":"Bitcoin","tr":"Bitcoin","ru":"биткоин","ja":"ビットコイン","zh":"比特币","zh-tw":"比特幣","ko":"비트코인","ar":"بيتكوين","th":"บิตคอยน์","id":"Bitcoin"},"image":{"thumb":"https://assets.coingecko.com/coins/images/1/thumb/bitcoin.png?1547033579","small":"https://assets.coingecko.com/coins/images/1/small/bitcoin.png?1547033579"},"market_data":{"current_price":{"aud":108.5381,"brl":221.2976,"btc":1.0,"cad":100.2328,"chf":89.9662,"cny":593.3071,"dkk":543.2916,"eur":72.8642,"gbp":63.3637,"hkd":749.7141,"idr":995513.5169,"inr":5896.3385,"jpy":9570.2338,"krw":108598.3713,"mxn":1228.6747,"myr":314.5932,"ngn":16607.2111308,"nzd":123.1737,"php":4214.3305,"pln":309.0587,"rub":3182.1916,"sek":637.5644,"sgd":123.0276,"twd":2904.2561,"uah":844.4927718,"usd":103.7,"xag":4.8574,"xau":0.0736,"xdr":63.9838,"zar":954.6352},"market_cap":{"aud":1248009062.135,"brl":2544557258.96,"btc":11498350.0,"cad":1152511815.88,"chf":1034462855.77,"cny":6822052693.285,"dkk":6246956968.86,"eur":837818074.07,"gbp":728577999.895,"hkd":8620475121.735,"idr":11446762847047.115,"inr":67798163791.475,"jpy":110041897814.23,"krw":1248702082637.355,"mxn":14127731736.745,"myr":3617302721.22,"ngn":190955526105.83417,"nzd":1416294313.395,"php":48457847104.675,"pln":3553665103.145,"rub":36589952783.86,"sek":7330938618.74,"sgd":1414614404.46,"twd":33394153127.435,"uah":9710273462.62653,"usd":1192378895.0,"xag":55852085.29,"xau":846278.56,"xdr":735708126.73,"zar":10976729651.920002},"total_volume":{"aud":0.0,"brl":0.0,"btc":0.0,"cad":0.0,"chf":0.0,"cny":0.0,"dkk":0.0,"eur":0.0,"gbp":0.0,"hkd":0.0,"idr":0.0,"inr":0.0,"jpy":0.0,"krw":0.0,"mxn":0.0,"myr":0.0,"ngn":0.0,"nzd":0.0,"php":0.0,"pln":0.0,"rub":0.0,"sek":0.0,"sgd":0.0,"twd":0.0,"uah":0.0,"usd":0.0,"xag":0.0,"xau":0.0,"xdr":0.0,"zar":0.0}},"community_data":{"facebook_likes":null,"twitter_followers":null,"reddit_average_posts_48h":0.0,"reddit_average_comments_48h":0.0,"reddit_subscribers":null,"reddit_accounts_active_48h":null},"developer_data":{"forks":null,"stars":null,"subscribers":null,"total_issues":null,"closed_issues":null,"pull_requests_merged":null,"pull_request_contributors":null,"code_additions_deletions_4_weeks":{"additions":null,"deletions":null},"commit_count_4_weeks":null},"public_interest_stats":{"alexa_rank":null,"bing_matches":null}}