{"id":"bitcoin","symbol":"btc","name":"Bitcoin","localization":{"en":"Bitcoin","de":"Bitcoin","es":"Bitcoin","fr":"Bitcoin","it":"Bitcoin","pl":"Bitcoin","ro":"Bitcoin","hu":"Bitcoin","nl":"Bitcoin","pt":"Bitcoin","sv":"Bitcoin","vi":"Bitcoin","tr":"Bitcoin","ru":"биткоин","ja":"ビットコイン","zh":"比特币","zh-tw":"比特幣","ko":"비트코인","ar":"بيتكوين","th":"บิตคอยน์","id":"Bitcoin"},"image":{"thumb":"https://assets.coingecko.com/coins/images/1/thumb/bitcoin.png?1547033579","small":"https://assets.coingecko.com/coins/images/1/small/bitcoin.png?1547033579"},"market_data":{"current_price":{"aud":916.3071,"bdt":79139.93100674001,"bhd":384.40264306,"bmd":1019.66,"brl":1950.1734,"btc":1.0,"cad":887.7683,"chf":745.3592,"cny":5080.3404,"dkk":4545.6288,"eur":608.5639,"gbp":510.1396,"hkd":6467.2577,"idr":9966960.8724,"inr":51162.1038,"jpy":85679.8452,"krw":882526.1674,"ltc":28.413530523235167,"mmk":1001996.7357179999,"mxn":10804.317,"myr":2692.1832,"ngn":161513.53118433998,"nzd":1006.969,"php":36670.0809,"pln":2552.1185,"rub":27373.9486,"sek":5424.8025,"sgd":1042.9182,"twd":24693.0395,"uah":8374.5287596,"usd":1019.66,"vef":6415.26124654,"xag":42.7981,"xau":0.6783,"xdr":542.0845,"zar":8630.3278},"market_cap":{"aud":11073250596.015,"bdt":956378367240.6006,"bhd":4645371400.4550295,"bmd":12322234219.0,"brl":23567162978.31,"btc":12084650.0,"cad":10728369186.595,"chf":9007405056.28,"cny":61394135614.86,"dkk":54932333077.92,"eur":7354281734.135,"gbp":6164858517.14,"hkd":78154545764.305,"idr":120447233706648.67,"inr":618276117686.67,"jpy":1035410941296.18,"krw":10665019848870.41,"ltc":343367571.63761383,"mmk":12108779852294.527,"mxn":130566389434.05,"myr":32534091707.88,"ngn":1951834494626.8342,"nzd":12168867925.85,"php":443145093148.185,"pln":30841458831.025,"rub":330804587948.99,"sek":65556839531.625,"sgd":12603301425.63,"twd":298406739793.675,"uah":101203248974.70015,"usd":12322234219.0,"vef":77526186822.9996,"xag":517200059.165,"xau":8197018.095,"xdr":6550901452.925,"zar":104294490848.26999},"total_volume":{"aud":0.0,"bdt":0.0,"bhd":0.0,"bmd":0.0,"brl":0.0,"btc":0.0,"cad":0.0,"chf":0.0,"cny":0.0,"dkk":0.0,"eur":0.0,"gbp":0.0,"hkd":0.0,"idr":0.0,"inr":0.0,"jpy":0.0,"krw":0.0,"ltc":0.0,"mmk":0.0,"mxn":0.0,"myr":0.0,"ngn":0.0,"nzd":0.0,"php":0.0,"pln":0.0,"rub":0.0,"sek":0.0,"sgd":0.0,"twd":0.0,"uah":0.0,"usd":0.0,"vef":0.0,"xag":0.0,"xau":0.0,"xdr":0.0,"zar":0.0}},"community_data":{"facebook_likes":null,"twitter_followers":null,"reddit_average_posts_48h":0.0,"reddit_average_comments_48h":0.0,"reddit_subscribers":null,"reddit_accounts_active_48h":null},"developer_data":{"forks":null,"stars":null,"subscribers":null,"total_issues":null,"closed_issues":null,"pull_requests_merged":null,"pull_request_contributors":null,"code_additions_deletions_4_weeks":{"additions":null,"deletions":null},"commit_count_4_weeks":null},"public_interest_stats":{"alexa_rank":null,"bing_matches":null}}